src/chrome-cookie-extractor/__init__.py
src/chrome-cookie-extractor/__main__.py
src/chrome-cookie-extractor/chrome_cookie_extractor.py
chrome_cookie_extractor-0.0.2.dist-info/METADATA
chrome_cookie_extractor-0.0.2.dist-info/WHEEL
chrome_cookie_extractor-0.0.2.dist-info/licenses/LICENSE
chrome_cookie_extractor-0.0.2.dist-info/RECORD
