Metadata-Version: 2.1
Name: chrome-cookie-extractor
Version: 0.0.2
Summary: chrome-cookie-extractor exports your cookies to the Netscape cookie file format which is compatible with wget, curl, youtube-dl and more.
Project-URL: Homepage, https://github.com/KroneCorylus/chrome-cookie-extractor
Project-URL: Bug Tracker, https://github.com/KroneCorylus/chrome-cookie-extractor/issues
Author-email: Krone <ahustinkrone@gmail.com>
License: MIT License
License-File: LICENSE
Classifier: License :: OSI Approved :: MIT License
Classifier: Operating System :: Unix
Classifier: Programming Language :: Python :: 3
Requires-Python: >=3.7
